{
  "path": "plugins/overview",
  "title": "Plugin Overview",
  "description": "Phantasy uses a code-first plugin framework built around:",
  "frontmatter": {},
  "content": "# Plugin Overview\n\nPhantasy uses a code-first plugin framework built around:\n\n- `src/plugins/base-plugin.ts`\n- `src/plugins/plugin-manager.ts`\n- `src/plugins/manager/builtin-plugins.ts`\n- `src/plugins/hook-bus.ts`\n\n## Built-In Plugins\n\nBuilt-ins are now profile-based rather than implicitly always-on.\n\n- `core-runtime`: no built-ins by default\n- `coder`: coding tools and diagnostics\n- `character`: companion identity, memory, voice, image, and presentation features\n- `server-admin`: operational and browser automation surfaces\n\nThe generated inventory is the source of truth for exact descriptors and privilege flags: [Built-in plugins](../generated/plugins.md).\n\n## Lifecycle\n\n`PluginManager` is responsible for:\n\n- registration\n- manifest validation\n- initialization\n- config validation and persistence\n- enable and disable state\n- tool aggregation\n- hook execution\n- destruction and unload\n\n## External Plugins\n\nExternal plugins remain supported, but the install path is intentionally stricter than before:\n\n- fetch package artifact\n- stage and inspect manifest\n- do not run lifecycle scripts during install\n- explicitly enable after verification\n\nThat keeps remote install from becoming silent code execution.\n\n## Profile Loading\n\nThe runtime resolves built-ins from selected profiles in config or environment. If no profile is requested, the system falls back to `core-runtime`.\n\nThat means the repo can support coding agents, companion businesses, and production products without pretending they all belong in one trusted base runtime.\n\n## Related Docs\n\n- [Design Principles](../architecture/design-principles.md)\n- [Runtime Packages](../architecture/runtime-packages.md)\n- [Developing Plugins](./developing.md)\n- [Integration Model](../integrations/integrations-guide.md)\n- [Generated Built-in Plugin Inventory](../generated/plugins.md)\n",
  "sourcePath": "src/docs/content/plugins/overview.md"
}
